vectorcalculus/__init__.py
vectorcalculus/decompositions.py
vectorcalculus/grid.py
vectorcalculus/integrals.py
vectorcalculus/interactive.py
vectorcalculus/numba_helpers.py
vectorcalculus/operations.py
vectorcalculus/symbolic.py
vectorcalculus/vector.py
vectorcalculus/visualization.py
vectorcalculus/perf/__init__.py
vectorcalculus/perf/numba_helpers.py
vectorcalculus-0.3.0.dist-info/licenses/LICENSE
vectorcalculus-0.3.0.dist-info/METADATA
vectorcalculus-0.3.0.dist-info/WHEEL
vectorcalculus-0.3.0.dist-info/top_level.txt
vectorcalculus-0.3.0.dist-info/RECORD
