Metadata-Version: 2.4
Name: vectorcalculus
Version: 0.3.0
Summary: Small pure-Python vector calculus utilities
License: MIT
Classifier: Programming Language :: Python :: 3
Classifier: License :: OSI Approved :: MIT License
Classifier: Operating System :: OS Independent
Requires-Python: >=3.8
License-File: LICENSE
Requires-Dist: numpy>=1.21
Provides-Extra: dev
Requires-Dist: pytest>=7.0; extra == "dev"
Provides-Extra: viz
Requires-Dist: plotly>=5.0; extra == "viz"
Dynamic: license-file
